windgrib/__init__.py
windgrib/grib.py
windgrib-0.2.0.dist-info/licenses/LICENSE
windgrib-0.2.0.dist-info/METADATA
windgrib-0.2.0.dist-info/WHEEL
windgrib-0.2.0.dist-info/top_level.txt
windgrib-0.2.0.dist-info/RECORD
