Metadata-Version: 2.4
Name: windgrib
Version: 0.2.0
Summary: A Python package for working with GRIB weather data files
Home-page: https://github.com/yorfy/windgrib
Author: Your Name
Author-email: Your Name <your.email@example.com>
Project-URL: Homepage, https://github.com/yorfy/windgrib
Project-URL: Bug Tracker, https://github.com/yorfy/windgrib/issues
Project-URL: Documentation, https://github.com/yorfy/windgrib/blob/main/README.md
Keywords: grib,weather,meteorology,data,forecast,weather-data,gfs,ecmwf
Classifier: Programming Language :: Python :: 3
Classifier: Programming Language :: Python :: 3.7
Classifier: Programming Language :: Python :: 3.8
Classifier: Programming Language :: Python :: 3.9
Classifier: Programming Language :: Python :: 3.10
Classifier: Programming Language :: Python :: 3.11
Classifier: Programming Language :: Python :: 3.12
Classifier: License :: OSI Approved :: MIT License
Classifier: Operating System :: OS Independent
Classifier: Intended Audience :: Developers
Classifier: Intended Audience :: Science/Research
Classifier: Topic :: Scientific/Engineering :: Atmospheric Science
Classifier: Development Status :: 3 - Alpha
Classifier: Natural Language :: English
Requires-Python: >=3.7
License-File: LICENSE
Requires-Dist: numpy>=1.20.0
Requires-Dist: pandas>=1.3.0
Requires-Dist: xarray>=0.20.0
Requires-Dist: s3fs>=2021.11.0
Requires-Dist: requests>=2.26.0
Requires-Dist: tqdm>=4.62.0
Requires-Dist: cfgrib>=0.9.10.0
Requires-Dist: dask>=2021.11.0
Requires-Dist: netCDF4>=1.6.0
Dynamic: license-file
